[
  {
    "id": "yamafuji-budoen",
    "name": "やまふじぶどう園（ホーライサンワイナリー）",
    "company": "やまふじぶどう園",
    "brand": "ホーライサン",
    "winery_type": "small",
    "founded": "1927",
    "founded_era": "昭和2年",
    "address": "富山県富山市婦中町みさご谷10",
    "tel": "076-469-4539",
    "url": "https://www.winery.co.jp/",
    "area": "富山市婦中町",
    "desc": "富山市婦中町でぶどう園を営み、自園果実を生かしたワインと観光農園を両立する老舗ワイナリー。",
    "visit": "ぶどう狩り・カフェ営業あり。",
    "wine_style": "red,dry_white,sparkling",
    "main_grape": "mba",
    "gi": "",
    "grapes": ["マスカット・ベーリーA", "メルロー", "ピオーネ", "ブラックビート", "サマーブラック", "ソーヴィニヨン・ブラン", "シャインマスカット"],
    "brands": ["ホーライサン"],
    "features": ["1927年創業の100年以上の歴史", "自園産ぶどうを活用した醸造", "ぶどう狩り体験も提供"],
    "nearest_station": "",
    "source": "https://www.winery.co.jp/",
    "lat": 36.6307,
    "lng": 137.1424,
    "name_en": "Yamafuji Budoen (Horaisan Winery)"
  },
  {
    "id": "says-farm",
    "name": "セイズ・ファーム",
    "company": "株式会社セイズファーム",
    "brand": "SAYS FARM",
    "winery_type": "estate",
    "founded": "2007",
    "founded_era": "平成19年",
    "address": "富山県氷見市余川字北山238",
    "tel": "",
    "url": "https://www.saysfarm.com/",
    "area": "氷見市",
    "desc": "氷見の丘陵から富山湾を望む立地で、畑・レストラン・宿を一体で運営する複合型エステートワイナリー。",
    "visit": "ワイナリー・農場・レストラン・ギャラリー・宿泊施設あり。",
    "wine_style": "dry_white,red,sparkling",
    "main_grape": "chardonnay",
    "gi": "",
    "grapes": ["シャルドネ", "ソーヴィニヨン・ブラン", "メルロー", "カベルネ・ソーヴィニヨン", "アルバリーニョ"],
    "brands": ["SAYS FARM"],
    "features": ["富山湾と立山連峰を望む丘陵地のワイナリー", "農場・レストラン・宿泊施設を併設するアグリツーリズム複合施設"],
    "nearest_station": "",
    "source": "https://www.saysfarm.com/",
    "lat": 36.8504,
    "lng": 136.9812,
    "name_en": "SAYS Farm"
  },
  {
    "id": "domaine-beau",
    "name": "ドメーヌボー",
    "company": "トレボー株式会社",
    "brand": "Domaine Beau",
    "winery_type": "estate",
    "founded": "2017",
    "founded_era": "平成29年",
    "address": "富山県南砺市立野原1197番地",
    "tel": "0763-77-4639",
    "url": "https://tresbeau.co.jp/",
    "area": "南砺市",
    "desc": "南砺の風土を反映したワインを掲げ、地元産ぶどうと欧州で培った知見を生かすエステートワイナリー。",
    "visit": "醸造所見学ツアーあり（要予約）。",
    "wine_style": "dry_white,red",
    "main_grape": "chardonnay",
    "gi": "",
    "grapes": ["シャルドネ"],
    "brands": ["Domaine Beau"],
    "features": ["「身土不二」の理念のもと地元の風土を反映したワイン造り", "30年以上のヨーロッパでの経験を活かす", "「一流の田舎」から世界の心を動かすワインを目指す"],
    "nearest_station": "",
    "source": "https://tresbeau.co.jp/",
    "lat": 36.5378,
    "lng": 136.8896,
    "name_en": "Domaine Beau"
  },
  {
    "id": "kanata-winery",
    "name": "カナタワイナリー",
    "company": "KANATA WINERY",
    "brand": "KANATA",
    "winery_type": "small",
    "founded": "2023",
    "founded_era": "令和5年",
    "address": "富山県魚津市天神野新字西大野147番1",
    "tel": "0765-55-2027",
    "url": "https://kanatawinery.com/",
    "area": "魚津市",
    "desc": "魚津市で2023年に始動した県東部初のワイナリー。地域の水循環と果樹栽培の伝統を背景に少量醸造を行う。",
    "visit": "営業日・見学対応は事前確認推奨。",
    "wine_style": "dry_white,red",
    "main_grape": "chardonnay",
    "gi": "",
    "grapes": ["シャルドネ", "ヤマソーヴィニヨン", "シャインマスカット"],
    "brands": ["KANATA"],
    "features": ["県東部初のワイナリー（2023年10月オープン）", "魚津の水循環と気候条件を活かした「世界水準のテロワール」", "地域の果樹栽培の伝統（約140年）を守りながら農業後継者不足の解決を目指す"],
    "nearest_station": "",
    "source": "https://kanatawinery.com/",
    "lat": 36.8191,
    "lng": 137.4103,
    "name_en": "Kanata Winery"
  }
]
